aus-senate-audit
setup.py
aus_senate_audit/__init__.py
aus_senate_audit/audit_recorder.py
aus_senate_audit/audit_tie_breaker.py
aus_senate_audit/audit_validator.py
aus_senate_audit/cli.py
aus_senate_audit/config_reader.py
aus_senate_audit/constants.py
aus_senate_audit.egg-info/PKG-INFO
aus_senate_audit.egg-info/SOURCES.txt
aus_senate_audit.egg-info/dependency_links.txt
aus_senate_audit.egg-info/requires.txt
aus_senate_audit.egg-info/top_level.txt
aus_senate_audit/audits/__init__.py
aus_senate_audit/audits/bayesian_audit.py
aus_senate_audit/sampler/__init__.py
aus_senate_audit/sampler/sampler.py
aus_senate_audit/sampler/sampler_wrapper.py
aus_senate_audit/senate_election/__init__.py
aus_senate_audit/senate_election/base_senate_election.py
aus_senate_audit/senate_election/real_senate_election.py
aus_senate_audit/senate_election/real_senate_election_results.py
aus_senate_audit/senate_election/simulated_senate_election.py