Metadata-Version: 1.0
Name: aus-senate-audit
Version: 0.13.0
Summary: Audit the Australian Senate Election.
Home-page: https://github.com/berjc/aus-senate-audit
Author: Berj Chilingirian
Author-email: berjc@mit.edu
License: Apache2
Keywords: senate voting audit
Platform: UNKNOWN
